sug_sock/Attribute.py
sug_sock/Server.py
sug_sock/__init__.py
sug_sock/client.py
sug_sock/sug_sock.py
sug_sock-0.0.7.dist-info/LICENCE.txt
sug_sock-0.0.7.dist-info/METADATA
sug_sock-0.0.7.dist-info/WHEEL
sug_sock-0.0.7.dist-info/top_level.txt
sug_sock-0.0.7.dist-info/RECORD
