Metadata-Version: 2.1
Name: sug-sock
Version: 0.0.7
Summary: suguv socket expantion pack
Home-page: https://bitbucket.org/SuguvHyde/sug_sock/src/master/
Author: Suguv
Author-email: orsegev7@gmail.com
License: MIT
Platform: UNKNOWN
